pyampact/__init__.py
pyampact/alignment.py
pyampact/alignmentUtils.py
pyampact/dataCompilation.py
pyampact/performance.py
pyampact/symbolic.py
pyampact/symbolicUtils.py
pyampact/version.py
pyampact-0.7.9.dist-info/METADATA
pyampact-0.7.9.dist-info/WHEEL
pyampact-0.7.9.dist-info/top_level.txt
pyampact-0.7.9.dist-info/RECORD
